timewsync/__init__.py
timewsync/__main__.py
timewsync/auth.py
timewsync/cli.py
timewsync/config.py
timewsync/dispatch.py
timewsync/file_parser.py
timewsync/interval.py
timewsync/io_handler.py
timewsync/json_converter.py
timewsync/logging_helpers.py
timewsync/paths.py
timewsync/tokenizer.py
timewsync-1.1.dist-info/LICENSE
timewsync-1.1.dist-info/METADATA
timewsync-1.1.dist-info/WHEEL
timewsync-1.1.dist-info/entry_points.txt
timewsync-1.1.dist-info/top_level.txt
timewsync-1.1.dist-info/RECORD
