Metadata-Version: 2.1
Name: timewsync
Version: 1.1
Summary: Timewarrior Synchronization client
Home-page: https://github.com/timewarrior-synchronize/timew-sync-client
License: MIT License
Project-URL: Bug Tracker, https://github.com/timewarrior-synchronize/timew-sync-client/issues
Project-URL: Wiki, https://github.com/timewarrior-synchronize/timew-sync-client/wiki
Classifier: Programming Language :: Python :: 3
Classifier: License :: OSI Approved :: MIT License
Requires-Python: >=3.8
License-File: LICENSE
Requires-Dist: colorama
Requires-Dist: jwcrypto
Requires-Dist: pyjwt
Requires-Dist: requests
Requires-Dist: importlib; python_version == "2.6"
